nonebot_plugin_HttpCat
