Metadata-Version: 2.1
Name: nonebot-plugin-HttpCat
Version: 0.0.2
Summary: _✨Nonebot猫猫http状态码插件✨_
Home-page: https://github.com/ANGJustinl/nonebot_plugin_HttpCat
Author: ANGJustinl
Author-email: angjustin@163.com
Keywords: pip,nonebot2,nonebot,nonebot_plugin
Platform: any
Classifier: Programming Language :: Python :: 3
Classifier: Operating System :: OS Independent
Requires-Python: >=3.7
